linalgtools/__init__.py
linalgtools/tools.py
linalgtools-0.0.1.dist-info/METADATA
linalgtools-0.0.1.dist-info/WHEEL
linalgtools-0.0.1.dist-info/licenses/LICENSE
linalgtools-0.0.1.dist-info/RECORD
