Metadata-Version: 2.1
Name: linalgtools
Version: 0.0.1
Summary: Some additional tools for solving specific problems in applied linear algebra.
Project-URL: Homepage, https://codeberg.org/HackTheOxidation/linalgtools
Project-URL: Bug Tracker, https://codeberg.org/HackTheOxidation/linalgtools/issues
Author-email: HackTheOxidation <tomas.hagenau@protonmail.ch>
License: MIT License
License-File: LICENSE
Classifier: License :: OSI Approved :: MIT License
Classifier: Operating System :: OS Independent
Classifier: Programming Language :: Python :: 3
Classifier: Topic :: Scientific/Engineering :: Mathematics
Requires-Python: >=3.8
Requires-Dist: sympy~=1.11.1
